{
  "ir_schema_version": 2,
  "capsule_id": "full-lecture_capsule",
  "source_hash": "full-lecture_hash",
  "source_title": "Full Lecture - Integrated AV",
  "version": 1,
  "total_duration": 15.0,
  "processed_at": "2026-07-15T00:00:00Z",
  "model_used": "mimo-v2.5",
  "evidences": [
    {
      "id": "ev_001",
      "content": "Purple background video presents lecture content with synchronized audio",
      "timestamp_start_sec": 0.0,
      "timestamp_end_sec": 15.0,
      "evidence_type": "concept",
      "speaker": "instructor",
      "confidence": 0.8
    }
  ]
}