{
  "annotation_version": "0.1.0",
  "media_path": "02 Building Environments - The Basics/02 What are PBR Materials.mp4",
  "annotator": "lin10",
  "annotation_date": "2026-07-15T00:00:00Z",
  "items": [
    {
      "item_id": "gt_ev_001",
      "kind": "quote",
      "type": "concept_explanation",
      "text": "PBR stands for Physically Based Rendering, a standard approach to materials.",
      "modality": "audio",
      "anchor": {
        "start_us": 0,
        "end_us": 20000000,
        "confidence": 1.0
      },
      "speaker": "instructor"
    },
    {
      "item_id": "gt_ev_002",
      "kind": "quote",
      "type": "definition",
      "text": "PBR materials have three core properties: Base Color, Roughness, and Metalness.",
      "modality": "audio",
      "anchor": {
        "start_us": 20000000,
        "end_us": 50000000,
        "confidence": 1.0
      },
      "speaker": "instructor"
    },
    {
      "item_id": "gt_ev_003",
      "kind": "quote",
      "type": "concept_explanation",
      "text": "Base Color defines the albedo of the surface without lighting.",
      "modality": "audio",
      "anchor": {
        "start_us": 50000000,
        "end_us": 90000000,
        "confidence": 1.0
      },
      "speaker": "instructor"
    },
    {
      "item_id": "gt_ev_004",
      "kind": "quote",
      "type": "concept_explanation",
      "text": "Roughness controls how smooth or rough a surface appears, affecting specular reflections.",
      "modality": "audio",
      "anchor": {
        "start_us": 90000000,
        "end_us": 130000000,
        "confidence": 1.0
      },
      "speaker": "instructor"
    },
    {
      "item_id": "gt_ev_005",
      "kind": "quote",
      "type": "definition",
      "text": "Metalness determines if a surface behaves like a metal or a dielectric.",
      "modality": "audio",
      "anchor": {
        "start_us": 130000000,
        "end_us": 180000000,
        "confidence": 1.0
      },
      "speaker": "instructor"
    },
    {
      "item_id": "gt_ev_006",
      "kind": "quote",
      "type": "procedure_step",
      "text": "Metals have colored specular reflections and no diffuse. Dielectrics have white specular.",
      "modality": "audio",
      "anchor": {
        "start_us": 180000000,
        "end_us": 230000000,
        "confidence": 1.0
      },
      "speaker": "instructor"
    },
    {
      "item_id": "gt_ev_007",
      "kind": "quote",
      "type": "concept_explanation",
      "text": "UE5 uses the Microfacet BRDF model for realistic surface rendering.",
      "modality": "audio",
      "anchor": {
        "start_us": 230000000,
        "end_us": 280000000,
        "confidence": 1.0
      },
      "speaker": "instructor"
    },
    {
      "item_id": "gt_ev_008",
      "kind": "quote",
      "type": "example",
      "text": "Example: A rusty metal pipe has high roughness but full metalness for a weathered look.",
      "modality": "audio",
      "anchor": {
        "start_us": 280000000,
        "end_us": 320000000,
        "confidence": 1.0
      },
      "speaker": "instructor"
    },
    {
      "item_id": "gt_ev_009",
      "kind": "quote",
      "type": "procedure_step",
      "text": "In Unreal, you create materials in the Material Editor using node-based graph.",
      "modality": "audio",
      "anchor": {
        "start_us": 320000000,
        "end_us": 345000000,
        "confidence": 1.0
      },
      "speaker": "instructor"
    }
  ],
  "claims": [
    {
      "claim_id": "gt_clm_001",
      "status": "supported",
      "statement": "PBR materials use Base Color, Roughness, and Metalness as core properties.",
      "evidence_ids": [
        "gt_ev_002",
        "gt_ev_003",
        "gt_ev_004",
        "gt_ev_005"
      ],
      "relation": "supports"
    },
    {
      "claim_id": "gt_clm_002",
      "status": "supported",
      "statement": "Metals and dielectrics have different reflection behavior in PBR rendering.",
      "evidence_ids": [
        "gt_ev_005",
        "gt_ev_006"
      ],
      "relation": "supports"
    }
  ],
  "gaps": [
    {
      "gap_id": "gt_gap_001",
      "description": "System missed specific numerical values for roughness/metalness parameter ranges",
      "modality": "audio",
      "expected_kind": "fact",
      "anchor": {
        "start_us": 180000000,
        "end_us": 230000000
      }
    }
  ],
  "conflicts": []
}