{
  "component": "whisper-cpp-tools",
  "version": "1.5.6",
  "platform": "windows-x86_64",
  "engine_api": 1,
  "description": "whisper.cpp native CLI transcription tools",
  "download_url": "https://github.com/ggml-org/whisper.cpp/releases/latest/download/whisper-bin-x64.zip",
  "archive_type": "zip",
  "sha256": "",
  "signature": "",
  "size_mb": 8,
  "requires": {},
  "provides": [
    "transcription-native"
  ],
  "files": [
    "whisper-cli.exe",
    "whisper.dll",
    "ggml.dll",
    "ggml-base.dll",
    "ggml-cpu-alderlake.dll",
    "ggml-cpu-cannonlake.dll",
    "ggml-cpu-cascadelake.dll",
    "ggml-cpu-haswell.dll",
    "ggml-cpu-icelake.dll",
    "ggml-cpu-sandybridge.dll",
    "ggml-cpu-skylakex.dll",
    "ggml-cpu-sse42.dll",
    "ggml-cpu-x64.dll"
  ],
  "package_sha256": ""
}
